[
  {
    "podcast_title": "Political – America Out Loud News",
    "podcast_author": "Political – America Out Loud News",
    "podcast_url": "https://www.americaoutloud.news/category/subject-matter/politics/feed/podcast/",
    "episode_title": "US faces urgent tech gaps in future warfare race",
    "description": "We must identify gaps in the supply chain…",
    "audio_url": "https://media.blubrry.com/1472134/ins.blubrry.com/1472134/U_S_faces_urgent_tech_gaps_in_future_warfare_race.mp3",
    "episode_id": 41301767506,
    "transcript": "Intro… (short demo transcript text here)"
  },
  {
    "podcast_title": "AMERICA OUT LOUD PODCAST NETWORK",
    "podcast_author": "AMERICA OUT LOUD PODCAST NETWORK",
    "podcast_url": "https://www.americaoutloud.news/feed/podcast/",
    "episode_title": "US faces urgent tech gaps in future warfare race",
    "description": "Federal acquisition considerations and risks to IP…",
    "audio_url": "https://media.blubrry.com/1472134/ins.blubrry.com/1472134/U_S_faces_urgent_tech_gaps_in_future_warfare_race.mp3",
    "episode_id": 41302041808,
    "transcript": "Another short transcript for the demo…"
  }
]